setup.py
scripts/can_logger.py
scripts/can_player.py
scripts/can_viewer.py
zhouch22/__init__.py
zhouch22/bit_timing.py
zhouch22/broadcastmanager.py
zhouch22/bus.py
zhouch22/ctypesutil.py
zhouch22/interface.py
zhouch22/listener.py
zhouch22/logger.py
zhouch22/message.py
zhouch22/notifier.py
zhouch22/player.py
zhouch22/thread_safe_bus.py
zhouch22/typechecking.py
zhouch22/util.py
zhouch22/viewer.py
zhouch22.egg-info/PKG-INFO
zhouch22.egg-info/SOURCES.txt
zhouch22.egg-info/dependency_links.txt
zhouch22.egg-info/requires.txt
zhouch22.egg-info/top_level.txt
zhouch22/interfaces/__init__.py
zhouch22/interfaces/canalystii.py
zhouch22/interfaces/iscan.py
zhouch22/interfaces/nican.py
zhouch22/interfaces/robotell.py
zhouch22/interfaces/slcan.py
zhouch22/interfaces/virtual.py
zhouch22/interfaces/vector/__init__.py
zhouch22/interfaces/vector/canlib.py
zhouch22/interfaces/vector/exceptions.py
zhouch22/interfaces/vector/xlclass.py
zhouch22/interfaces/vector/xldefine.py
zhouch22/interfaces/vector/xldriver.py
zhouch22/io/__init__.py
zhouch22/io/asc.py
zhouch22/io/blf.py
zhouch22/io/canutils.py
zhouch22/io/csv.py
zhouch22/io/generic.py
zhouch22/io/logger.py
zhouch22/io/player.py
zhouch22/io/printer.py
zhouch22/io/sqlite.py